{"last":"2026-03-12","mi":{"n":2140,"m":"2026-03"},"cur":2149,"cmt":{"1963":"03-09","2026":"03-09","1902":"03-08","2121":"03-10","2145":"03-10","2146":"03-10","2039":"03-11","2119":"03-12","1917":"03-12"},"prs":{"2133":"test-hierarchy","2134":"timeout","2135":"release","2136":"DOTNET_ROOT","2139":"IsTestProject","2141":"paths","2142":"perf","2149":"dotrush"},"issues":{"2144":"inlineValues","2147":"inlineValues","2148":"inlineValues"},"n":"1917:comment+fix needed. 1963:blocked. Next:1620,1622,1637"}
